{
      "infolist": [
            {
                  "filename": "0_clone_BN-NEWEST"
            },
            {
                  "filename": "8_clone_BN-NEWEST"
            },
            {
                  "filename": "1_clone_BN-NEWEST"
            },
            {
                  "filename": "7_clone_BN-NEWEST"
            },
            {
                  "filename": "3_clone_BN-NEWEST"
            },
            {
                  "filename": "2_clone_BN-NEWEST"
            },
            {
                  "filename": "4_clone_BN-NEWEST"
            },
            {
                  "filename": "10_clone_BN-NEWEST"
            },
            {
                  "filename": "5_clone_BN-NEWEST"
            },
            {
                  "filename": "6_clone_BN-NEWEST"
            },
            {
                  "filename": "9_clone_BN-NEWEST"
            }
      ]
}